{
  "id": "skilltree:miner_subclass_2_life_notable_1",
  "bonuses": [
    {
      "type": "skilltree:crafted_item_bonus",
      "item_condition": {
        "tag_id": "curios:necklace",
        "type": "skilltree:tag"
      },
      "item_bonus": {
        "skill_bonus": {
          "attribute": "minecraft:generic.max_health",
          "id": "298c5e09-39a7-4bf0-8d14-de013da55de6",
          "name": "SkillBonus",
          "amount": 3.0,
          "operation": 0,
          "player_multiplier": {
            "type": "skilltree:none"
          },
          "player_condition": {
            "type": "skilltree:none"
          },
          "type": "skilltree:attribute"
        },
        "type": "skilltree:skill_bonus"
      }
    }
  ],
  "directConnections": [],
  "longConnections": [],
  "oneWayConnections": [],
  "tags": [],
  "backgroundTexture": "skilltree:textures/icons/background/notable.png",
  "iconTexture": "skilltree:textures/icons/miner_subclass_2_life_notable_1.png",
  "borderTexture": "skilltree:textures/tooltip/notable.png",
  "titleColor": "",
  "positionX": -325.9333,
  "positionY": 307.06915,
  "buttonSize": 20,
  "isStartingPoint": false
}